{
  "name": {
    "tr": "İngiltere Hava Kargo",
    "en": "England Air Cargo"
  },
  "status": "play",
  "category": "",
  "id": "og033372qy",
  "url": "",
  "path": "ingiltere-hava-kargo",
  "index": 9,
  "desing": {
    "header": [],
    "body": [],
    "footer": []
  },
  "pathnext": "",
  "description": {
    "tr": "İngiltere Hava Kargo ile İngiltere'ye güvenli taşıma. Kapıdan kapıya, gümrük ve sigorta. Fiyat için iletişime geçin.",
    "en": "England Air Cargo service. England cargo, door to door delivery. Customs and insurance. Get a quote for England Air Cargo."
  },
  "desc": {},
  "icon": "home",
  "keyword": {
    "tr": "ingiltere kargo, ingiltere nakliyat, ingiltere-hava-kargo, eve den eve taşıma, uluslararası nakliye",
    "en": "england cargo, england shipping, england-air-cargo, door to door moving, international shipping"
  },
  "text": {
    "tr": "<h2>İngiltere Hava Kargo</h2><p>İngiltere Hava Kargo hizmetimizde eşyalarınızı Türkiye'den İngiltere'ye güvenle taşıyoruz. Bu hizmete özel paketleme ve takip seçenekleri sunuyoruz.</p><h3>İngiltere Hava Kargo Nasıl Yapılır?</h3><p>Önce eşya listesi ve adres bilgilerinizi alıyoruz. Sonra İngiltere Hava Kargo kapsamında size özel fiyat ve süre bildiriyoruz. Gümrük işlemleri ve sigorta dahil planlıyoruz.</p><ul><li>İngiltere Hava Kargo için özel paketleme</li><li>Kapıdan kapıya teslimat</li><li>Gümrük danışmanlığı</li><li>Sigorta seçenekleri</li></ul><p>İngiltere Hava Kargo sürecinde sorularınız için müşteri hizmetlerimiz yanınızda. İngiltere adresinize kadar takip ve teslimat garantisi veriyoruz.</p><p>İngiltere Hava Kargo taleplerinizde deneyimli ekibimiz, süre ve maliyet açısından şeffaf bir hizmet sunar. Londra, Manchester, Birmingham ve tüm İngiltere için İngiltere Hava Kargo fiyat teklifi alabilirsiniz.</p><p>İngiltere Hava Kargo taleplerinizde deneyimli ekibimiz, süre ve maliyet açısından şeffaf bir hizmet sunar. Londra, Manchester, Birmingham ve tüm İngiltere için İngiltere Hava Kargo fiyat teklifi alabilirsiniz.</p><p>İngiltere Hava Kargo taleplerinizde deneyimli ekibimiz, süre ve maliyet açısından şeffaf bir hizmet sunar. Londra, Manchester, Birmingham ve tüm İngiltere için İngiltere Hava Kargo fiyat teklifi alabilirsiniz.</p><p>İngiltere Hava Kargo taleplerinizde deneyimli ekibimiz, süre ve maliyet açısından şeffaf bir hizmet sunar. Londra, Manchester, Birmingham ve tüm İngiltere için İngiltere Hava Kargo fiyat teklifi alabilirsiniz.</p><p>İngiltere Hava Kargo taleplerinizde deneyimli ekibimiz, süre ve maliyet açısından şeffaf bir hizmet sunar. Londra, Manchester, Birmingham ve tüm İngiltere için İngiltere Hava Kargo fiyat teklifi alabilirsiniz.</p><p>İngiltere Hava Kargo taleplerinizde deneyimli ekibimiz, süre ve maliyet açısından şeffaf bir hizmet sunar. Londra, Manchester, Birmingham ve tüm İngiltere için İngiltere Hava Kargo fiyat teklifi alabilirsiniz.</p><p>İngiltere Hava Kargo taleplerinizde deneyimli ekibimiz, süre ve maliyet açısından şeffaf bir hizmet sunar. Londra, Manchester, Birmingham ve tüm İngiltere için İngiltere Hava Kargo fiyat teklifi alabilirsiniz.</p><p>İngiltere Hava Kargo taleplerinizde deneyimli ekibimiz, süre ve maliyet açısından şeffaf bir hizmet sunar. Londra, Manchester, Birmingham ve tüm İngiltere için İngiltere Hava Kargo fiyat teklifi alabilirsiniz.</p><p>İngiltere Hava Kargo taleplerinizde deneyimli ekibimiz, süre ve maliyet açısından şeffaf bir hizmet sunar. Londra, Manchester, Birmingham ve tüm İngiltere için İngiltere Hava Kargo fiyat teklifi alabilirsiniz.</p><p>İngiltere Hava Kargo taleplerinizde deneyimli ekibimiz, süre ve maliyet açısından şeffaf bir hizmet sunar. Londra, Manchester, Birmingham ve tüm İngiltere için İngiltere Hava Kargo fiyat teklifi alabilirsiniz.</p><p>İngiltere Hava Kargo taleplerinizde deneyimli ekibimiz, süre ve maliyet açısından şeffaf bir hizmet sunar. Londra, Manchester, Birmingham ve tüm İngiltere için İngiltere Hava Kargo fiyat teklifi alabilirsiniz.</p>",
    "en": "<h2>England Air Cargo</h2><p><b>England Air Cargo</b> – We offer safe and cost-effective shipping between England and Turkey. Door to door delivery, customs handling and insurance options.</p><p>Our experienced team handles house moves, international shipping and groupage cargo. Contact us for a quote.</p><h3>Why Choose Us</h3><ul><li>Door to door delivery</li><li>Customs support</li><li>Insured shipping</li><li>Competitive rates</li><li>On-time delivery</li></ul><p>For sending goods to England, house moving or commercial cargo, we are here. Expert service for England Air Cargo.</p><p>We ship your goods safely to England. Delivery to London, Manchester, Birmingham and all UK addresses. Door to door moving from Turkey to England, groupage and container options available. Contact us for a quote.</p><p>We ship your goods safely to England. Delivery to London, Manchester, Birmingham and all UK addresses. Door to door moving from Turkey to England, groupage and container options available. Contact us for a quote.</p><p>We ship your goods safely to England. Delivery to London, Manchester, Birmingham and all UK addresses. Door to door moving from Turkey to England, groupage and container options available. Contact us for a quote.</p><p>We ship your goods safely to England. Delivery to London, Manchester, Birmingham and all UK addresses. Door to door moving from Turkey to England, groupage and container options available. Contact us for a quote.</p><p>We ship your goods safely to England. Delivery to London, Manchester, Birmingham and all UK addresses. Door to door moving from Turkey to England, groupage and container options available. Contact us for a quote.</p><p>We ship your goods safely to England. Delivery to London, Manchester, Birmingham and all UK addresses. Door to door moving from Turkey to England, groupage and container options available. Contact us for a quote.</p><p>We ship your goods safely to England. Delivery to London, Manchester, Birmingham and all UK addresses. Door to door moving from Turkey to England, groupage and container options available. Contact us for a quote.</p><p>We ship your goods safely to England. Delivery to London, Manchester, Birmingham and all UK addresses. Door to door moving from Turkey to England, groupage and container options available. Contact us for a quote.</p><p>We ship your goods safely to England. Delivery to London, Manchester, Birmingham and all UK addresses. Door to door moving from Turkey to England, groupage and container options available. Contact us for a quote.</p><p>We ship your goods safely to England. Delivery to London, Manchester, Birmingham and all UK addresses. Door to door moving from Turkey to England, groupage and container options available. Contact us for a quote.</p><p>We ship your goods safely to England. Delivery to London, Manchester, Birmingham and all UK addresses. Door to door moving from Turkey to England, groupage and container options available. Contact us for a quote.</p><p>We ship your goods safely to England. Delivery to London, Manchester, Birmingham and all UK addresses. Door to door moving from Turkey to England, groupage and container options available. Contact us for a quote.</p>"
  },
  "update": "2026-02-09T10:33:47.535Z",
  "date": "2026-02-09T10:22:13.179Z",
  "spot": {
    "en": "England Air Cargo – England cargo and shipping. Safe delivery.",
    "tr": "İngiltere Hava Kargo – İngiltere kargo ve nakliye. Güvenli taşıma."
  }
}